{"Document":{"longName":"Document","type":"Document","camt.036.001.01":{"longName":"camt.036.001.01","type":"camt.036.001.01","Assgnmt":{"longName":"指派","type":"CaseAssignment","Id":{"longName":"标识","type":"Max35Text"},"Assgnr":{"longName":"指派人","type":"AnyBICIdentifier"},"Assgne":{"longName":"受派人","type":"AnyBICIdentifier"},"CreDtTm":{"longName":"创建时间","type":"ISODateTime"}},"Case":{"longName":"案例","type":"Case","Id":{"longName":"标识","type":"Max35Text"},"Cretr":{"longName":"创建方","type":"AnyBICIdentifier"},"ReopCaseIndctn":{"longName":"案例应答标识","type":"YesNoIndicator"}},"Conf":{"longName":"确认","type":"DebitAuthorisationConfirmation","DbtAuthstn":{"longName":"借记授权","type":"YesNoIndicator"},"AmtToDbt":{"longName":"借入金额","type":"CurrencyAndAmount"},"ValDtToDbt":{"longName":"借记起息日","type":"ISODate"},"Rsn":{"longName":"原因","type":"Max140Text"}}}},"name":"camt.036.001.01_dict_zh"}